deepwireless/__init__.py
deepwireless/plotter.py
deepwireless/simulator.py
deepwireless-0.9.3.dist-info/METADATA
deepwireless-0.9.3.dist-info/WHEEL
deepwireless-0.9.3.dist-info/licenses/LICENSE
deepwireless-0.9.3.dist-info/RECORD
